odoo/addons/product_video_link/README.rst
odoo/addons/product_video_link/__init__.py
odoo/addons/product_video_link/__manifest__.py
odoo/addons/product_video_link/demo/product_demo.xml
odoo/addons/product_video_link/i18n/product_video_link.pot
odoo/addons/product_video_link/models/__init__.py
odoo/addons/product_video_link/models/product_category.py
odoo/addons/product_video_link/models/product_template.py
odoo/addons/product_video_link/readme/CONTRIBUTORS.rst
odoo/addons/product_video_link/readme/DESCRIPTION.rst
odoo/addons/product_video_link/readme/USAGE.rst
odoo/addons/product_video_link/security/ir.model.access.csv
odoo/addons/product_video_link/static/description/icon.png
odoo/addons/product_video_link/static/description/index.html
odoo/addons/product_video_link/views/product_category_view.xml
odoo/addons/product_video_link/views/product_template_view.xml
odoo14_addon_product_video_link-14.0.1.0.2.dist-info/METADATA
odoo14_addon_product_video_link-14.0.1.0.2.dist-info/WHEEL
odoo14_addon_product_video_link-14.0.1.0.2.dist-info/top_level.txt
odoo14_addon_product_video_link-14.0.1.0.2.dist-info/RECORD
